LICENSE
MANIFEST.in
README.md
requirements.txt
setup.py
oxasl_surfpvc/__init__.py
oxasl_surfpvc/_version.py
oxasl_surfpvc/api.py
oxasl_surfpvc.egg-info/PKG-INFO
oxasl_surfpvc.egg-info/SOURCES.txt
oxasl_surfpvc.egg-info/dependency_links.txt
oxasl_surfpvc.egg-info/requires.txt
oxasl_surfpvc.egg-info/top_level.txt